hs_eps_gateway/__init__.py
hs_eps_gateway/client.py
hs_eps_gateway/config-main.py
hs_eps_gateway/config.py
hs_eps_gateway/eps_types.py
hs_eps_gateway/utils.py
hs_eps_gateway-1.0.1.dist-info/licenses/LICENSE
hs_eps_gateway-1.0.1.dist-info/METADATA
hs_eps_gateway-1.0.1.dist-info/WHEEL
hs_eps_gateway-1.0.1.dist-info/top_level.txt
hs_eps_gateway-1.0.1.dist-info/RECORD
