Metadata-Version: 2.4
Name: hs-eps-gateway
Version: 1.0.1
Summary: Python Easy Payment Gateway SDK.
Author-email: Himel <contact@himelrana.com>
License-Expression: MIT
Project-URL: Homepage, https://pypi.org/project/hs-eps-gateway/
Project-URL: Repository, https://github.com/Swe-HimelRana/hs_eps_gateway
Classifier: Programming Language :: Python :: 3
Classifier: Operating System :: OS Independent
Requires-Python: >=3.7
License-File: LICENSE
Requires-Dist: annotated-types==0.7.0
Requires-Dist: certifi==2025.7.14
Requires-Dist: charset-normalizer==3.4.2
Requires-Dist: idna==3.10
Requires-Dist: pydantic==2.11.7
Requires-Dist: pydantic_core==2.33.2
Requires-Dist: requests==2.32.4
Requires-Dist: typing-inspection==0.4.1
Requires-Dist: typing_extensions==4.14.1
Requires-Dist: urllib3==2.5.0
Dynamic: license-file
